kaldibin/__init__.py
kaldibin/featbin.py
kaldibin/latbin.py
kaldibin/adapters/__init__.py
kaldibin/adapters/context.py
kaldibin/adapters/io.py
kaldibin-0.1.0.dist-info/LICENSE
kaldibin-0.1.0.dist-info/METADATA
kaldibin-0.1.0.dist-info/WHEEL
kaldibin-0.1.0.dist-info/top_level.txt
kaldibin-0.1.0.dist-info/RECORD
