Metadata-Version: 2.1
Name: kaldibin
Version: 0.1.0
Summary: Python wrappers for Kaldi executables. Still in a partially-implemented, proof-of-concept stage.
Home-page: https://github.com/rcgale/kaldibin
Author: Robert Gale
Author-email: rcgale@gmail.com
License: UNKNOWN
Platform: UNKNOWN
